sccover/__init__.py
sccover/graph.py
sccover/stats.py
sccover-0.0.1.dist-info/METADATA
sccover-0.0.1.dist-info/WHEEL
sccover-0.0.1.dist-info/top_level.txt
sccover-0.0.1.dist-info/RECORD
